hitchpage/__init__.py
hitchpage/model.py
hitchpage-0.3.0.dist-info/LICENSE.txt
hitchpage-0.3.0.dist-info/METADATA
hitchpage-0.3.0.dist-info/WHEEL
hitchpage-0.3.0.dist-info/top_level.txt
hitchpage-0.3.0.dist-info/RECORD
