Metadata-Version: 2.1
Name: hitchpage
Version: 0.3.0
Summary: Page config model library.
Author-email: Colm O'Connor <colm.oconnor.github@gmail.com>
License: Elastic License 2.0
Project-URL: homepage, https://hitchdev.com/hitchpage
Project-URL: documentation, https://hitchdev.com/hitchpage/using
Project-URL: repository, https://github.com/hitchdev/hitchpage
Project-URL: changelog, https://hitchdev.com/hitchpage/changelog
Keywords: yaml,hitchdev,bdd,tdd,playwright,tests
Classifier: Programming Language :: Python :: 3
Classifier: Topic :: Software Development :: Quality Assurance
Classifier: Topic :: Software Development :: Testing
Classifier: Topic :: Text Processing :: Markup
Classifier: Topic :: Software Development :: Libraries
Classifier: Natural Language :: English
Classifier: Environment :: Console
Requires-Python: >=3.7.0
License-File: LICENSE.txt
Requires-Dist: strictyaml >=1.4.3
Requires-Dist: playwright >=1.24.1
